[{"Company Name":"Company Name","Privacy Policy":"Privacy Policy","Data Broker Email":"Data Broker Email","Location":"Location","Data Broker Allows Opt-Out?":"Data Broker Allows Opt-Out?"},{"Company Name":"1-800-US-Search","Privacy Policy":"https://peopleconnect.us/privacy-policy","Data Broker Email":"privacy@peopleconnect.us","Location":"Washington","Data Broker Allows Opt-Out?":"Yes - by Opt-Out Form"},{"Company Name":"411.com","Privacy Policy":"https://www.411.com/data-policy","Data Broker Email":"support@whitepages.com","Location":"Washington","Data Broker Allows Opt-Out?":"Unclear"},{"Company Name":"Accucom","Privacy Policy":"","Data Broker Email":"","Location":"Massachusetts","Data Broker Allows Opt-Out?":"No"},{"Company Name":"Active Intel Investigations Llc","Privacy Policy":"","Data Broker Email":"","Location":"Texas","Data Broker Allows Opt-Out?":"No"},{"Company Name":"Acxiom Llc","Privacy Policy":"https://acxiom.com/about-us/privacy","Data Broker Email":"privacy@acxiom.com","Location":"Arizona","Data Broker Allows Opt-Out?":"Yes - by Opt-Out Form"},{"Company Name":"Address Search","Privacy Policy":"http://www.addresssearch.com/privacy-policy.php","Data Broker Email":"","Location":"","Data Broker Allows Opt-Out?":"Yes - by Opt-Out Form"},{"Company Name":"Addresses.Com","Privacy Policy":"http://www.peopleconnect.us/privacy","Data Broker Email":"","Location":"Washington","Data Broker Allows Opt-Out?":"No"},{"Company Name":"Advanced Background Checks","Privacy Policy":"http://www.advancedbackgroundchecks.com/privacy ; https://www.advancedbackgroun…","Data Broker Email":"","Location":"California","Data Broker Allows Opt-Out?":"Unclear"},{"Company Name":"Advantage Sales & Marketing Llc","Privacy Policy":"https://www.advantagesolutions.net/pages/privacy","Data Broker Email":"alex@take5mg.com","Location":"California","Data Broker Allows Opt-Out?":"Unclear"},{"Company Name":"Advertise4Sales Llc","Privacy Policy":"","Data Broker Email":"tapster@gmail.com","Location":"Washington","Data Broker Allows Opt-Out?":"Unclear"},{"Company Name":"All Web Leads Inc","Privacy Policy":"http://www.allwebleads.com/privacy","Data Broker Email":"onlineops@allwebleads.com","Location":"Texas","Data Broker Allows Opt-Out?":"Unclear"},{"Company Name":"Allareacodes.Com","Privacy Policy":"http://www.allareacodes.com/policies.htm","Data Broker Email":"press@allareacodes.com","Location":"Missouri","Data Broker Allows Opt-Out?":"Yes - by Opt-Out Form"},{"Company Name":"Archives","Privacy Policy":"https://www.ancestry.com/cs/legal/privacystatement?hideHeader=1","Data Broker Email":"dpo@ancestry.com","Location":"California","Data Broker Allows Opt-Out?":"Yes - by email"},{"Company Name":"Asl Marketing Inc","Privacy Policy":"http://aslmarketing.com/privacy-policy/","Data Broker Email":"info@aslmarketing.com","Location":"New York","Data Broker Allows Opt-Out?":"No"},{"Company Name":"Background Check International (Bci)","Privacy Policy":"","Data Broker Email":"kit@bcint.com","Location":"","Data Broker Allows Opt-Out?":"No"},{"Company Name":"Background-Check-Only.Com","Privacy Policy":"http://www.background-check-only.com/privacy-policy.htm","Data Broker Email":"","Location":"","Data Broker Allows Opt-Out?":"No"},{"Company Name":"Backgroundchecks.Com Llc","Privacy Policy":"https://www.backgroundchecks.com/privacypolicy","Data Broker Email":"cklafehn@backgroundchecks.com","Location":"Texas","Data Broker Allows Opt-Out?":"Unclear"},{"Company Name":"Belardi Ostroy Alc Llc/ Belardi Wong","Privacy Policy":"https://www.belardiwong.com/privacypolicy","Data Broker Email":"sherry.booles@alc.com","Location":"New York","Data Broker Allows Opt-Out?":"Unclear"},{"Company Name":"Blockshopper","Privacy Policy":"https://blockshopper.com/privacy-policy","Data Broker Email":"","Location":"Missouri","Data Broker Allows Opt-Out?":"Unclear"},{"Company Name":"Bridgevine Inc.","Privacy Policy":"https://www.bridgevine.com/privacy-policy/","Data Broker Email":"dwayne.landry@bridgevine.com","Location":"Georgia","Data Broker Allows Opt-Out?":"No"},{"Company Name":"Business Profiles","Privacy Policy":"http://businessprofiles.com/privacy","Data Broker Email":"","Location":"Oklahoma","Data Broker Allows Opt-Out?":"Unclear"},{"Company Name":"Cell Phone Registry","Privacy Policy":"http://cellphoneregistry.com/index.php?xpath=privacy","Data Broker Email":"","Location":"","Data Broker Allows Opt-Out?":"Yes - by Opt-Out Form"},{"Company Name":"Census Info Us","Privacy Policy":"http://www.census-info.us/privacy","Data Broker Email":"","Location":"","Data Broker Allows Opt-Out?":"No"},{"Company Name":"Cic Mortgage Credit Inc.","Privacy Policy":"https://www.ciccredit.com/information-security-policy-and-guideline/","Data Broker Email":"CTHOMAS@CICCREDIT.COM","Location":"Tennessee","Data Broker Allows Opt-Out?":"No"},{"Company Name":"Compact Information Systems","Privacy Policy":"http://www.compactlists.com/privacy-policy.html","Data Broker Email":"pei@compactlists.com","Location":"Washington","Data Broker Allows Opt-Out?":"Unclear"},{"Company Name":"Confi-Chek","Privacy Policy":"","Data Broker Email":"customercare@peoplefinders.com","Location":"California","Data Broker Allows Opt-Out?":"No"},{"Company Name":"Contemporary Information Corp.","Privacy Policy":"https://www.cicreports.com/consumer-assistance/#privacypolicy","Data Broker Email":"compliance@cicreports.com","Location":"California","Data Broker Allows Opt-Out?":"Unclear"},{"Company Name":"Corelogic Credco Of Puerto Rico","Privacy Policy":"https://www.corelogic.com/privacy.aspx","Data Broker Email":"dghazaleh@corelogic.com","Location":"","Data Broker Allows Opt-Out?":""},{"Company Name":"Corporation Wiki","Privacy Policy":"http://www.corporationwiki.com/privacy-policy","Data Broker Email":"","Location":"Florida","Data Broker Allows Opt-Out?":"Unclear"},{"Company Name":"Court Records","Privacy Policy":"http://www.courtrecords.org/index.php?xpath=privacy","Data Broker Email":"privacy@cisnationwide.com","Location":"Massachusetts","Data Broker Allows Opt-Out?":"Yes - by Opt-Out Form"},{"Company Name":"Court Registry","Privacy Policy":"http://courtregistry.org/index.php?xpath=privacy","Data Broker Email":"privacy@cisnationwide.com","Location":"","Data Broker Allows Opt-Out?":"Yes - by Opt-Out Form"},{"Company Name":"Criminal Background Records","Privacy Policy":"http://www.criminalbackgroundrecords.com/privacy.html","Data Broker Email":"privacy@criminalbackgroundchecks.com","Location":"Massachusetts","Data Broker Allows Opt-Out?":"No"},{"Company Name":"Criminal Pages","Privacy Policy":"http://www.criminalpages.com/privacy/","Data Broker Email":"","Location":"Washington","Data Broker Allows Opt-Out?":"Yes - by Opt-Out Form"},{"Company Name":"Criminal Screen","Privacy Policy":"http://www.criminalscreen.com/privacy.cfm","Data Broker Email":"Webmaster@CriminalScreen.com","Location":"Florida","Data Broker Allows Opt-Out?":"No"},{"Company Name":"Criminal Watch Dog","Privacy Policy":"https://www.criminalwatchdog.com/Privacy-Policy.aspx","Data Broker Email":"","Location":"Massachusetts","Data Broker Allows Opt-Out?":"No"},{"Company Name":"Cupidscreen","Privacy Policy":"https://cupidscreen.com/privacy-policy/","Data Broker Email":"info@onlineinvestigations.com.au","Location":"","Data Broker Allows Opt-Out?":"No"},{"Company Name":"Dataamerican.Com","Privacy Policy":"http://www.dataamerica.com/pages/privacy-policy/","Data Broker Email":"info@dataamerica.com","Location":"New York","Data Broker Allows Opt-Out?":"No"},{"Company Name":"Databaseusa.Com Llc","Privacy Policy":"https://databaseusa.com/index.php/privacy-policy/","Data Broker Email":"consult@databaseusa.com","Location":"Nebraska","Data Broker Allows Opt-Out?":"Yes - by email"},{"Company Name":"Datamentors Llc Dba V12","Privacy Policy":"https://v12data.com/v12-privacy-point-of-view/","Data Broker Email":"pkuman@v12data.com","Location":"Florida","Data Broker Allows Opt-Out?":"Unclear"},{"Company Name":"Datamyx Llc Dba Deluxe Marketing Solutions","Privacy Policy":"https://fi.deluxe.com/datamyx-privacy/","Data Broker Email":"privacyprogramoffice@deluxe.com","Location":"Florida","Data Broker Allows Opt-Out?":"Unclear"},{"Company Name":"Datax Ltd","Privacy Policy":"http://dataxltd.com/privacy-policy/","Data Broker Email":"vtinquiries@equifax.com","Location":"Nevada","Data Broker Allows Opt-Out?":"Unclear"},{"Company Name":"Death Records","Privacy Policy":"http://deathrecords.org/index.php?xpath=privacy","Data Broker Email":"privacy@cisnationwide.com","Location":"Massachusetts","Data Broker Allows Opt-Out?":"Unclear"},{"Company Name":"Digital Media Solutions","Privacy Policy":"https://digitalmediasolutions.com/privacy-policy","Data Broker Email":"connect@theDMSgrp.com","Location":"Florida","Data Broker Allows Opt-Out?":"Yes - by email"},{"Company Name":"Divorce Records","Privacy Policy":"http://www.divorcerecords.org/index.php?xpath=privacy","Data Broker Email":"privacy@cisnationwide.com","Location":"Massachusetts","Data Broker Allows Opt-Out?":"Unclear"},{"Company Name":"Drobu Media Llc","Privacy Policy":"","Data Broker Email":"Dblackman@drobu.com","Location":"New York","Data Broker Allows Opt-Out?":"No"},{"Company Name":"Easy Background Check","Privacy Policy":"","Data Broker Email":"","Location":"Washington","Data Broker Allows Opt-Out?":"No"},{"Company Name":"Easybackgrounds.Com","Privacy Policy":"https://www.easybackgrounds.com/privacy-policy","Data Broker Email":"WSep@ghrr.com","Location":"New Hampshire","Data Broker Allows Opt-Out?":"No"},{"Company Name":"Email Tracer","Privacy Policy":"http://www.emailtracer.com/privacy.php","Data Broker Email":"","Location":"Massachusetts","Data Broker Allows Opt-Out?":"No"},{"Company Name":"Enformion","Privacy Policy":"https://www.enformion.com/en/privacy/","Data Broker Email":"angela.arriaga@enformion.com","Location":"California","Data Broker Allows Opt-Out?":"No"},{"Company Name":"Equifax Information Services Llc","Privacy Policy":"https://www.equifax.com/privacy/myequifaxservices/","Data Broker Email":"vtinquiries@equifax.com","Location":"Georgia","Data Broker Allows Opt-Out?":"Unclear"},{"Company Name":"Experian Data Corp","Privacy Policy":"https://www.experian.com/privacy/prod_serv_policy.html","Data Broker Email":"unsubscribe@experian.com","Location":"California","Data Broker Allows Opt-Out?":"Yes - by Opt-Out Form"},{"Company Name":"First American Data Tree Llc","Privacy Policy":"https://www.datatree.com/privacy-policy","Data Broker Email":"britchie-boland@firstam.com","Location":"California","Data Broker Allows Opt-Out?":"No"},{"Company Name":"First Orion Corporation","Privacy Policy":"https://firstorion.com/privacy-policy/","Data Broker Email":"cdenton@firstorion.com","Location":"Arizona","Data Broker Allows Opt-Out?":"Unclear"},{"Company Name":"Free Background Check","Privacy Policy":"http://freebackgroundcheck.us/privacy.php","Data Broker Email":"","Location":"Massachusetts","Data Broker Allows Opt-Out?":"No"},{"Company Name":"Freecellsearch.Com","Privacy Policy":"http://freecellsearch.com/privacypolicy.php","Data Broker Email":"support@freecellsearch.com","Location":"","Data Broker Allows Opt-Out?":"No"},{"Company Name":"General Information Solutions Llc","Privacy Policy":"https://www.hireright.com/legal/privacy-policy","Data Broker Email":"kristin.jones@hireright.com","Location":"South Carolina","Data Broker Allows Opt-Out?":"No"},{"Company Name":"Goodhire","Privacy Policy":"https://www.goodhire.com/privacy","Data Broker Email":"privacy@goodhire.com","Location":"California","Data Broker Allows Opt-Out?":"Unclear"},{"Company Name":"Govarrestrecords.Org","Privacy Policy":"http://www.govarrestrecords.org/privacy.html","Data Broker Email":"","Location":"North Carolina","Data Broker Allows Opt-Out?":"No"},{"Company Name":"Governmentregistry.Org","Privacy Policy":"http://governmentregistry.org/index.php?xpath=privacy","Data Broker Email":"privacy@cisnationwide.com","Location":"Massachusetts","Data Broker Allows Opt-Out?":"Unclear"},{"Company Name":"Govregistry.Us","Privacy Policy":"http://govregistry.us/privacy.php","Data Broker Email":"privacy@cisnationwide.com","Location":"Massachusetts","Data Broker Allows Opt-Out?":"Unclear"},{"Company Name":"Healthcare.Com","Privacy Policy":"https://www.healthcare.com/info/privacy-policy","Data Broker Email":"info@healthcare.com","Location":"Florida","Data Broker Allows Opt-Out?":"Unclear"},{"Company Name":"Ihs Markit","Privacy Policy":"https://ihsmarkit.com/Legal/privacy.html","Data Broker Email":"bruce.noll@ihsmarkit.com","Location":"Michigan","Data Broker Allows Opt-Out?":"Unclear"},{"Company Name":"Incheck Inc","Privacy Policy":"https://incheck.net/privacy-policy-pdf/","Data Broker Email":"abby@incheck.net","Location":"Wisconsin","Data Broker Allows Opt-Out?":"Unclear"},{"Company Name":"Info Pay","Privacy Policy":"https://www.infopay.com/privacy.php","Data Broker Email":"","Location":"Massachusetts","Data Broker Allows Opt-Out?":"Yes - by email"},{"Company Name":"Infocore Inc.","Privacy Policy":"https://infocore.com/infocore-privacy-policy/","Data Broker Email":"info@infocore.com","Location":"California","Data Broker Allows Opt-Out?":"No"},{"Company Name":"Infogroup Inc.","Privacy Policy":"https://www.infogroup.com/privacy-policy","Data Broker Email":"privacyteam@infogroup.com","Location":"Nebraska","Data Broker Allows Opt-Out?":"Yes - by email"},{"Company Name":"Infotracer","Privacy Policy":"https://members.infotracer.com/customer/terms?tab=privacy","Data Broker Email":"support@infotracer.com","Location":"Massachusetts","Data Broker Allows Opt-Out?":"Yes - by Opt-Out Form"},{"Company Name":"Infutor Data Solutions","Privacy Policy":"https://infutor.com/company/data-privacy/","Data Broker Email":"pedrokialanda@infutor.com","Location":"Illinois","Data Broker Allows Opt-Out?":"Yes - by Opt-Out Form"},{"Company Name":"Instant People Finder","Privacy Policy":"http://www.instantpeoplefinder.com/privacy.html","Data Broker Email":"","Location":"Washington","Data Broker Allows Opt-Out?":"Yes - by Opt-Out Form"},{"Company Name":"Instantbackgroundreport.Com","Privacy Policy":"http://instantbackgroundreport.com/index.php?xpath=privacy","Data Broker Email":"privacy@cisnationwide.com","Location":"Massachusetts","Data Broker Allows Opt-Out?":"Unclear"},{"Company Name":"Intel Registry","Privacy Policy":"http://intelregistry.com/privacy.php","Data Broker Email":"support@intelregistry.com","Location":"","Data Broker Allows Opt-Out?":"Yes - by Opt-Out Form"},{"Company Name":"Inteligator","Privacy Policy":"http://www.inteligator.com/home/privacy.php","Data Broker Email":"","Location":"","Data Broker Allows Opt-Out?":"Unclear"},{"Company Name":"Intelius","Privacy Policy":"http://www.peopleconnect.us/privacy","Data Broker Email":"privacy@peopleconnect.us","Location":"Washington","Data Broker Allows Opt-Out?":"Yes - by Opt-Out Form"},{"Company Name":"Intellireal Llc","Privacy Policy":"https://www.equifax.com/privacy/","Data Broker Email":"vtinquiries@equifax.com","Location":"Georgia","Data Broker Allows Opt-Out?":"No"},{"Company Name":"Ixi Corporation","Privacy Policy":"https://www.equifax.com/privacy/","Data Broker Email":"vtinquiries@equifax.com","Location":"Georgia","Data Broker Allows Opt-Out?":"No"},{"Company Name":"Kbm Group Llc","Privacy Policy":"https://www.kbmg.com/about-us/privacy/","Data Broker Email":"privacy@wundermandata.com","Location":"Colorado","Data Broker Allows Opt-Out?":"Yes - by email"},{"Company Name":"Kgbpeople","Privacy Policy":"http://www.kgbpeople.com/privacy-policy","Data Broker Email":"accounts@kgb.com","Location":"New York","Data Broker Allows Opt-Out?":"No"},{"Company Name":"Lexisnexis Risk Solutions Inc. And Affiliates","Privacy Policy":"https://risk.lexisnexis.com/privacy-policy","Data Broker Email":"legal.compliance@risk.lexisnexis.com","Location":"Georgia","Data Broker Allows Opt-Out?":"Unclear"},{"Company Name":"Libertydata.Net","Privacy Policy":"http://www.libertydata.net/privacypolicy.asp","Data Broker Email":"support@libertydata.net","Location":"Florida","Data Broker Allows Opt-Out?":"Yes - by email"},{"Company Name":"Locate People","Privacy Policy":"https://members.infotracer.com/customer/terms?tab=privacy","Data Broker Email":"support@infotracer.com","Location":"Massachusetts","Data Broker Allows Opt-Out?":"Yes - by Opt-Out Form"},{"Company Name":"Locatefamily.Com","Privacy Policy":"http://www.locatefamily.com/privacy_policy.html","Data Broker Email":"","Location":"New York","Data Broker Allows Opt-Out?":"Unclear"},{"Company Name":"Mapsmoji","Privacy Policy":"http://mapsmoji.com/privacy/","Data Broker Email":"email@mapsmoji.com","Location":"California","Data Broker Allows Opt-Out?":"No"},{"Company Name":"Marriage Records","Privacy Policy":"http://www.marriagerecords.org/index.php?xpath=privacy","Data Broker Email":"privacy@cisnationwide.com","Location":"","Data Broker Allows Opt-Out?":"Unclear"},{"Company Name":"Martin Data Llc","Privacy Policy":"","Data Broker Email":"mrichard@usinfosearch.com","Location":"Ohio","Data Broker Allows Opt-Out?":"Unclear"},{"Company Name":"Mocavo Inc.","Privacy Policy":"http://www.mocavo.com/privacy","Data Broker Email":"privacy@findmypast.co.uk","Location":"","Data Broker Allows Opt-Out?":"Unclear"},{"Company Name":"National Background Check","Privacy Policy":"http://www.nationalbackgroundcheck.com/privacy.htm","Data Broker Email":"contactus@nationalbackgroundcheck.com","Location":"Ohio","Data Broker Allows Opt-Out?":"No"},{"Company Name":"National Student Clearinghouse","Privacy Policy":"https://studentclearinghouse.org/about/our-privacy-commitment/","Data Broker Email":"legal@studentclearinghouse.org","Location":"Virginia","Data Broker Allows Opt-Out?":"Unclear"},{"Company Name":"Onlinesearches (Publicrecords.Onlinesearches.Com)","Privacy Policy":"https://publicrecords.onlinesearches.com/privacy-policy","Data Broker Email":"privacy@peopleconnect.us","Location":"Washington","Data Broker Allows Opt-Out?":"Yes - by Opt-Out Form"},{"Company Name":"Openonline","Privacy Policy":"http://www.openonline.com/Home/About-Us/Privacy-Statement.aspx","Data Broker Email":"compliance@openonline.com","Location":"Ohio","Data Broker Allows Opt-Out?":"Unclear"},{"Company Name":"Parasol Media Inc.","Privacy Policy":"https://v2.parasolleads.com/parasolleads-privacy-policy/","Data Broker Email":"jschwartz@parasolleads.com","Location":"California","Data Broker Allows Opt-Out?":"Unclear"},{"Company Name":"Partners Credit And Verification Solutions","Privacy Policy":"http://www.partnerscredit.com/pcvs_privacy.html","Data Broker Email":"pkarbo@creditinterlink.com","Location":"Illinois","Data Broker Allows Opt-Out?":"Unclear"},{"Company Name":"Path2Response","Privacy Policy":"https://path2response.com/privacy/","Data Broker Email":"invoices@path2response.com","Location":"Colorado","Data Broker Allows Opt-Out?":"Yes - by Opt-Out Form"},{"Company Name":"Peek You","Privacy Policy":"http://www.peekyou.com/privacy","Data Broker Email":"info@peekyou.com","Location":"New York","Data Broker Allows Opt-Out?":"Yes - by Opt-Out Form"},{"Company Name":"People By Name","Privacy Policy":"http://www.peoplebyname.com/privacy.php","Data Broker Email":"support@peoplebyname.com","Location":"Florida","Data Broker Allows Opt-Out?":"Yes - by Opt-Out Form"},{"Company Name":"People Finder: Instant Online Records Retrieval","Privacy Policy":"http://www.peoplefinderonline.net/privacy.html","Data Broker Email":"support@infotracer.com","Location":"","Data Broker Allows Opt-Out?":"Yes - by Opt-Out Form"},{"Company Name":"People Lookup (Data Source Intelius)","Privacy Policy":"http://peoplelookup.com/privacy-faq.php","Data Broker Email":"privacy@peoplelookup.com","Location":"Washington","Data Broker Allows Opt-Out?":"Yes - by Opt-Out Form"},{"Company Name":"Peopleaz.Org","Privacy Policy":"http://peopleaz.org/privacy.awx","Data Broker Email":"","Location":"","Data Broker Allows Opt-Out?":"No"},{"Company Name":"Peopleg2","Privacy Policy":"http://www.peopleg2.com/resources/privacy-policy.html","Data Broker Email":"","Location":"California","Data Broker Allows Opt-Out?":"No"},{"Company Name":"Peoplesmart","Privacy Policy":"http://www.peoplesmart.com/?_act=privacy","Data Broker Email":"privacy@peoplesmart.com","Location":"Nebraska","Data Broker Allows Opt-Out?":"Yes - by Opt-Out Form"},{"Company Name":"Persopo","Privacy Policy":"http://info.persopo.com/privacy-policy.html","Data Broker Email":"support@persopo.com","Location":"Nevada","Data Broker Allows Opt-Out?":"Yes - by Opt-Out Form"},{"Company Name":"Phone Registry","Privacy Policy":"http://www.phoneregistry.com/privacy.php","Data Broker Email":"","Location":"Massachusetts","Data Broker Allows Opt-Out?":"Yes - by Opt-Out Form"},{"Company Name":"Phonebooks.Com (Affiliated With Intelius)","Privacy Policy":"http://www.phonebooks.com/privacy.html","Data Broker Email":"help@phonebooks.com","Location":"","Data Broker Allows Opt-Out?":"Yes - by Opt-Out Form"},{"Company Name":"Plural Marketing Solutions Inc.","Privacy Policy":"","Data Broker Email":"george@plmrkg.com","Location":"New Jersey","Data Broker Allows Opt-Out?":"Unclear"},{"Company Name":"Plusaddress.Com","Privacy Policy":"https://plusaddress.com/#privacy","Data Broker Email":"info@plusaddresscom","Location":"","Data Broker Allows Opt-Out?":"Yes - by Opt-Out Form"},{"Company Name":"Possiblenow Data Services","Privacy Policy":"https://www.possiblenow.com/privacy-statement","Data Broker Email":"bschorer@possiblenow.com","Location":"Georgia","Data Broker Allows Opt-Out?":"Yes - by email"},{"Company Name":"Project Applecart Llc","Privacy Policy":"","Data Broker Email":"matt@applecart.co","Location":"New York","Data Broker Allows Opt-Out?":"No"},{"Company Name":"Public Arrest Records","Privacy Policy":"http://www.publicarrestrecords.org/privacy-policy-terms-of-use/","Data Broker Email":"","Location":"","Data Broker Allows Opt-Out?":"Yes - by email"},{"Company Name":"Public Record Site","Privacy Policy":"http://www.public-record-site.com/privacy-policy.htm","Data Broker Email":"privacy@1and1.com","Location":"Pennsylvania","Data Broker Allows Opt-Out?":"No"},{"Company Name":"Public Records Checks","Privacy Policy":"http://publicrecordschecks.com/privacy.php","Data Broker Email":"privacy@cisnationwide.com","Location":"Massachusetts","Data Broker Allows Opt-Out?":"Unclear"},{"Company Name":"Publicrecords.Com (Affiliated With Intelius)","Privacy Policy":"https://secure.publicrecords.com/privacy.php","Data Broker Email":"privacy@publicrecords.com","Location":"Washington","Data Broker Allows Opt-Out?":"Yes - by Opt-Out Form"},{"Company Name":"Publicrecordssearchonline.Org","Privacy Policy":"https://publicrecordssearchonline.org/privacy/","Data Broker Email":"contact@publicrecordssearchonline.org","Location":"","Data Broker Allows Opt-Out?":"No"},{"Company Name":"Quality Planning Corporation","Privacy Policy":"https://www.verisk.com/privacy-trademarks-use/iso-online-privacy-notice/","Data Broker Email":"jvolk@verisk.com","Location":"California","Data Broker Allows Opt-Out?":"No"},{"Company Name":"Records Authority","Privacy Policy":"http://recordsauthority.com/access/privacy.php","Data Broker Email":"privacy@cisnationwide.com","Location":"Massachusetts","Data Broker Allows Opt-Out?":"Unclear"},{"Company Name":"Reveal Mobile Inc","Privacy Policy":"https://revealmobile.com/privacy/","Data Broker Email":"andy@revealmobile.com","Location":"North Carolina","Data Broker Allows Opt-Out?":"Yes - by email"},{"Company Name":"Reverse Genie","Privacy Policy":"http://www.reversegenie.com/privacy.php","Data Broker Email":"privacy@cisnationwide.com","Location":"Massachusetts","Data Broker Allows Opt-Out?":"Unclear"},{"Company Name":"Reverse Mobile","Privacy Policy":"http://www.reversemobile.com/index.php?xpath=privacy","Data Broker Email":"privacy@cisnationwide.com","Location":"Massachusetts","Data Broker Allows Opt-Out?":"Unclear"},{"Company Name":"Reverse Number Database","Privacy Policy":"http://reversenumberdatabase.com/privacy","Data Broker Email":"privacy@cisnationwide.com","Location":"Massachusetts","Data Broker Allows Opt-Out?":"Unclear"},{"Company Name":"Reverse Phone Lookup","Privacy Policy":"http://www.reversephonelookup.com/privacy.html","Data Broker Email":"","Location":"","Data Broker Allows Opt-Out?":"Yes - by Opt-Out Form"},{"Company Name":"Reverserecords.Org","Privacy Policy":"http://reverserecords.org/index.php?xpath=privacy&code=","Data Broker Email":"support@infotracer.com","Location":"Massachusetts","Data Broker Allows Opt-Out?":"Yes - by email"},{"Company Name":"Roots Web (Associated With Ancestry.Com)","Privacy Policy":"https://www.ancestry.com/cs/privacyphilosophy","Data Broker Email":"content@ancestry.com","Location":"California","Data Broker Allows Opt-Out?":"Unclear"},{"Company Name":"Ruf Strategic Solutions","Privacy Policy":"https://ruf.com/privacy-policy/","Data Broker Email":"matthussey@infutor.com","Location":"Kansas","Data Broker Allows Opt-Out?":"Yes - by email"},{"Company Name":"Search Bug","Privacy Policy":"http://www.searchbug.com/privacy.aspx","Data Broker Email":"","Location":"California","Data Broker Allows Opt-Out?":"No"},{"Company Name":"Snoopstation.Com/","Privacy Policy":"http://www.snoopstation.com/privacy.php","Data Broker Email":"privacy@peopleconnect.us","Location":"Washington","Data Broker Allows Opt-Out?":"No"},{"Company Name":"Sorted By Birthdate.Com","Privacy Policy":"http://sortedbybirthdate.com/privacy.html","Data Broker Email":"webmaster@oklavoters.com","Location":"New Hampshire","Data Broker Allows Opt-Out?":"No"},{"Company Name":"Sorted By Name","Privacy Policy":"http://sortedbyname.com/privacy.html","Data Broker Email":"webmaster@oklavoters.com","Location":"New Hampshire","Data Broker Allows Opt-Out?":"No"},{"Company Name":"State Records (United States State Records)","Privacy Policy":"http://www.staterecords.org/index.php?xpath=privacy","Data Broker Email":"","Location":"Massachusetts","Data Broker Allows Opt-Out?":"Yes - by Opt-Out Form"},{"Company Name":"Sterling","Privacy Policy":"https://www.sterlingcheck.com/about/privacy/","Data Broker Email":"privacy@sterlingts.com","Location":"New York","Data Broker Allows Opt-Out?":"No"},{"Company Name":"Sterling Data Llc","Privacy Policy":"","Data Broker Email":"info@sterlingd.com","Location":"Virginia","Data Broker Allows Opt-Out?":"Yes - by email"},{"Company Name":"Strategic Information Resources","Privacy Policy":"https://strategicinfo.com/wp-content/uploads/SIR_Privacy_Statement-Jan2016.pdf","Data Broker Email":"jdrziak@strategicinfo.com","Location":"Massachusetts","Data Broker Allows Opt-Out?":"Unclear"},{"Company Name":"Superpages","Privacy Policy":"https://www.superpages.com/about/privacy.html","Data Broker Email":"","Location":"Texas","Data Broker Allows Opt-Out?":"Unclear"},{"Company Name":"Talx Corporation","Privacy Policy":"https://www.theworknumber.com/privacy-policy/","Data Broker Email":"vtinquiries@equifax.com","Location":"Missouri","Data Broker Allows Opt-Out?":"Unclear"},{"Company Name":"Tenant Detective","Privacy Policy":"http://www.tenantdetective.com/privacypolicy.php","Data Broker Email":"privacy@cisnationwide.com","Location":"","Data Broker Allows Opt-Out?":"Yes - by email"},{"Company Name":"Thatsthem","Privacy Policy":"https://thatsthem.com/privacy-policy","Data Broker Email":"info@ThatsThem.com","Location":"Washington","Data Broker Allows Opt-Out?":"Yes - by Opt-Out Form"},{"Company Name":"Thomas Reuters (Crc) Llc (D/B/A Refinitiv)","Privacy Policy":"https://www.refinitiv.com/en/policies/privacy-statement","Data Broker Email":"privacy.enquiries@refinitiv.com","Location":"Connecticut","Data Broker Allows Opt-Out?":"No"},{"Company Name":"Tlo Online Investigative Systems","Privacy Policy":"https://www.tlo.com/privacy","Data Broker Email":"TLOxpSupport@transunion.com","Location":"Florida","Data Broker Allows Opt-Out?":"No"},{"Company Name":"Transunion","Privacy Policy":"https://www.transunion.com/legal/privacy-policy","Data Broker Email":"keith.mccawley@transunion.com","Location":"Illinois","Data Broker Allows Opt-Out?":"Yes - by Opt-Out Form"},{"Company Name":"Ucc411","Privacy Policy":"http://www.ucc411.com/privacy-policy.aspx","Data Broker Email":"info@andersonadvisors.com","Location":"Nevada","Data Broker Allows Opt-Out?":"Unclear"},{"Company Name":"Ultimatewhitepages","Privacy Policy":"http://www.detectiveunlimited.com/privacy-policy.html","Data Broker Email":"webmaster@ultimatewhitepages.org","Location":"Washington","Data Broker Allows Opt-Out?":"No"},{"Company Name":"Ultimatewhitepages ","Privacy Policy":"http://www.detectiveunlimited.com/privacy-policy.html","Data Broker Email":"webmaster@ultimatewhitepages.org","Location":"Washington","Data Broker Allows Opt-Out?":"No"},{"Company Name":"Valley Yellow Pages (Myyp.Com)","Privacy Policy":"http://www.myyp.com/privacy","Data Broker Email":"vyp@myyp.com","Location":"California","Data Broker Allows Opt-Out?":"No"},{"Company Name":"Viant Technology Llc","Privacy Policy":"https://www.viantinc.com/privacy-policy/","Data Broker Email":"bnojima@viantinc.com","Location":"California","Data Broker Allows Opt-Out?":"Unclear"},{"Company Name":"Voter Factory","Privacy Policy":"http://www.voterfactory.com/Privacy.html","Data Broker Email":"help@VoterFactory.com","Location":"","Data Broker Allows Opt-Out?":"No"},{"Company Name":"Webbula Llc","Privacy Policy":"https://webbula.com/privacy-policy/","Data Broker Email":"privacy@webbula.com","Location":"Pennsylvania","Data Broker Allows Opt-Out?":"Yes - by Opt-Out Form"},{"Company Name":"West Publishing Corporation","Privacy Policy":"https://www.thomsonreuters.com/en/privacy-statement.html#legitimate-interests","Data Broker Email":"sonya.southward@thomsonreuters.com","Location":"Minnesota","Data Broker Allows Opt-Out?":"Yes - by Opt-Out Form"},{"Company Name":"Whitepages+","Privacy Policy":"https://whitepages.plus/privacy","Data Broker Email":"mail@whitepages.plus","Location":"California","Data Broker Allows Opt-Out?":"No"},{"Company Name":"Yasni","Privacy Policy":"http://www.yasni.com/privacy","Data Broker Email":"info@yasni.com","Location":"","Data Broker Allows Opt-Out?":"Yes - by email"},{"Company Name":"Ypstate.Com","Privacy Policy":"http://www.ypstate.com/wiki/ypstate/contactus/","Data Broker Email":"","Location":"","Data Broker Allows Opt-Out?":"No"},{"Company Name":"Zabasearch","Privacy Policy":"http://www.peopleconnect.us/privacy","Data Broker Email":"privacy@peopleconnect.us","Location":"Washington","Data Broker Allows Opt-Out?":"Yes - by Opt-Out Form"},{"Company Name":"Zoominfo.Com","Privacy Policy":"http://www.zoominfo.com/business/about-zoominfo/privacy-policy","Data Broker Email":"privacy@zoominfo.com","Location":"Massachusetts","Data Broker Allows Opt-Out?":"Yes - by email"}]